cx_logger/__init__.py
cx_logger/async_logger.py
cx_logger/file_handler.py
cx_logger/handler.py
cx_logger/levels.py
cx_logger/logger.py
cx_logger/logs_manager.py
cx_logger/stderr_handler.py
cx_logger/stdout_handler.py
cx_logger/sync_logger.py
cx_logger-2025.10.23.post4.dist-info/licenses/LICENSE
cx_logger-2025.10.23.post4.dist-info/METADATA
cx_logger-2025.10.23.post4.dist-info/WHEEL
cx_logger-2025.10.23.post4.dist-info/top_level.txt
cx_logger-2025.10.23.post4.dist-info/RECORD
